MANIFEST.in
README.rst
setup.cfg
setup.py
bin/pfcon
pfcon/__init__.py
pfcon/pfcon.py
pfcon/swiftmanager.py
pfcon.egg-info/PKG-INFO
pfcon.egg-info/SOURCES.txt
pfcon.egg-info/dependency_links.txt
pfcon.egg-info/not-zip-safe
pfcon.egg-info/requires.txt
pfcon.egg-info/top_level.txt