Metadata-Version: 1.0
Name: pfcon
Version: 2.2.4.6
Summary: (Python) Process and File Controller
Home-page: https://github.com/FNNDSC/pfcon
Author: Rudolph Pienaar
Author-email: rudolph.pienaar@gmail.com
License: MIT
Platform: UNKNOWN
